dumbo_ae/__init__.py
dumbo_ae/__main__.py
dumbo_ae/cli.py
dumbo_ae-0.1.4.dist-info/LICENSE
dumbo_ae-0.1.4.dist-info/WHEEL
dumbo_ae-0.1.4.dist-info/METADATA
dumbo_ae-0.1.4.dist-info/RECORD
