Metadata-Version: 2.1
Name: dumbo-ae
Version: 0.1.4
Summary: CLI per il corso di Architettura degli Elaboratori
Author: Mario Alviano
Author-email: mario.alviano@gmail.com
Requires-Python: >=3.10,<4.0
Classifier: Programming Language :: Python :: 3
Classifier: Programming Language :: Python :: 3.10
Classifier: Programming Language :: Python :: 3.11
Requires-Dist: dumbo-utils (>=0.1.6,<0.2.0)
Requires-Dist: requests (>=2.28.2,<3.0.0)
